Workbook

Sheet Historicals
A1: Europris ASA historical financials, FY2021 to FY2025
A2: All figures NOK million unless stated.
A4: Line item | C4: FY2021 | D4: FY2022 | E4: FY2023 | F4: FY2024 | G4: FY2025 | I4: Source and check
A6: INCOME STATEMENT
A7: Segment Norway sales | C7: 8648 | D7: 9016 | E7: 9467 | F7: 9878 | G7: 10590 | I7: AR2025 p15 Segment Norway. 2021-23 = group total, no Sweden segment existed
A8: Segment Sweden sales | C8: 0 | D8: 0 | E8: 0 | F8: 2873 | G8: 4289 | I8: AR2025 p17 Segment Sweden. OoB owned 8 months of 2024, full year 2025
A9: Other income and eliminations | C9: 0 | D9: 0 | E9: 0 | F9: -1 | G9: -1 | I9: Balancing figure. Group total less the two segments, rounding only
A10: Total operating income | C10: 8648 | D10: 9016 | E10: 9467 | F10: 12750 | G10: 14878
A11: Cost of goods sold | C11: 4592 | D11: 4833 | E11: 5276 | F11: 7437 | G11: 8799 | I11: Group key income statement figures, Key figures page of each report
A12: Gross profit | C12: 4056 | D12: 4183 | E12: 4191 | F12: 5313 | G12: 6079
A13: Gross margin | C13: 0.46901018 | D13: 0.46395297 | E13: 0.44269568 | F13: 0.41670588 | G13: 0.40858986
A14: Operating expenses | C14: 1973 | D14: 2132 | E14: 2222 | F14: 3153 | G14: 3700 | I14: Group key income statement figures. Opex line, post IFRS 16
A15: EBITDA | C15: 2083 | D15: 2051 | E15: 1969 | F15: 2160 | G15: 2379
A16: EBITDA margin | C16: 0.24086494 | D16: 0.22748447 | E16: 0.20798563 | F16: 0.16941176 | G16: 0.15990052
A17: Depreciation and amortisation | C17: 571 | D17: 611 | E17: 675 | F17: 923 | G17: 1060 | I17: Derived as reported EBITDA less reported EBIT. Cross check against the cash flow statement
A18: EBIT | C18: 1512 | D18: 1440 | E18: 1294 | F18: 1237 | G18: 1319
A19: EBIT margin | C19: 0.17483811 | D19: 0.15971606 | E19: 0.13668533 | F19: 0.097019608 | G19: 0.088654389
A20: Net financial items | C20: -94 | D20: -103 | E20: -143 | F20: -168 | G20: -265 | I20: Derived as profit before tax less EBIT. Negative because it is a net cost
A21: Profit before tax | C21: 1418 | D21: 1337 | E21: 1151 | F21: 1069 | G21: 1054
A22: Tax expense | C22: 314 | D22: 295 | E22: 243 | F22: 231 | G22: 245 | I22: Consolidated income statement, Income tax expense line, note 11
A23: Net profit | C23: 1104 | D23: 1042 | E23: 908 | F23: 838 | G23: 809
A25: CASH FLOW AND BALANCE SHEET
A26: Capital expenditure | C26: 131 | D26: 143 | E26: 142 | F26: 138 | G26: 131 | I26: Group key cash flow and balance sheet figures. Excludes right of use additions
A27: Change in net working capital | C27: -139 | D27: -374 | E27: 281 | F27: -211 | G27: -396 | I27: As reported. Negative means cash absorbed. This row is informational, the DCF does not read it
A28: Net interest bearing debt excluding leases | C28: 526 | D28: 626 | E28: 371 | F28: 720 | G28: 858 | I28: Net debt ex lease liabilities line, Group key cash flow and balance sheet figures
A29: Lease liabilities | C29: 1914 | D29: 2537 | E29: 2669 | F29: 3461 | G29: 3434 | I29: 2022 restated in AR2023 to include current leases. 2021 is on the old non current basis
A30: Shares outstanding, million | C30: 161 | D30: 160.9 | E30: 161.2 | F30: 162.7 | G30: 163.6 | I30: 2024 and 2025 are weighted average ordinary shares, note 17. Earlier years derived from EPS
A32: OPERATING METRICS
A33: Europris chain stores, Norway | C33: 270 | D33: 276 | E33: 282 | F33: 283 | G33: 289 | I33: Europris chain key figures, total number of chain stores at end of period
A34: OoB chain stores, Sweden | C34: 0 | D34: 0 | E34: 0 | F34: 93 | G34: 92 | I34: OoB chain key figures, AR2025 p17
A35: Like for like sales growth, Norway | C35: 0.015 | D35: -0.011 | E35: 0.026 | F35: 0.035 | G35: 0.063 | I35: Growth in like for like chain sales, Europris chain key figures

Sheet Price Data
A1: Price data
A2: Yahoo Finance five-year weekly data through 2026-08-23: EPR.OL Adjusted Close and OSEBX.OL Close. 261 aligned prices and 260 weekly returns.
A4: Date | B4: EPR.OL adjusted close | C4: OSEBX.OL close | D4: EPR weekly return | E4: Index weekly return
A5: 44438 | B5: 47.404076 | C5: 1161.86
A6: 44445 | B6: 46.753136 | C6: 1152.02 | D6: -0.013731729 | E6: -0.0084691494
A7: 44452 | B7: 46.98288 | C7: 1141.17 | D7: 0.0049139797 | E7: -0.0094182179
A8: 44459 | B8: 44.915176 | C8: 1155 | D8: -0.044009717 | E8: 0.012119102
A9: 44466 | B9: 43.881317 | C9: 1164.4301 | D9: -0.023018038 | E9: 0.0081645487
A10: 44473 | B10: 44.034485 | C10: 1167.35 | D10: 0.0034904997 | E10: 0.0025075975
A11: 44480 | B11: 45.183208 | C11: 1197.5699 | D11: 0.026086909 | E11: 0.02588767
A12: 44487 | B12: 46.485096 | C12: 1217.71 | D12: 0.028813525 | E12: 0.016817402
A13: 44494 | B13: 47.786983 | C13: 1192.78 | D13: 0.028006557 | E13: -0.020472799
A14: 44501 | B14: 47.786983 | C14: 1232.48 | D14: 0 | E14: 0.033283548
A15: 44508 | B15: 49.739819 | C15: 1233.4301 | D15: 0.040865419 | E15: 0.00077086302
A16: 44515 | B16: 48.897419 | C16: 1222.8 | D16: -0.016936121 | E16: -0.008618247
A17: 44522 | B17: 47.786983 | C17: 1174.9301 | D17: -0.022709491 | E17: -0.039147852
... A265: 46258 | B265: 89.099998 | C265: 2099.8501 | D265: 0.018285697 | E265: 0.0029948792

Sheet Beta
A1: Regression output
A2: Regression uses completed weekly returns. The cost-of-capital block uses the Blume-adjusted beta and remains auditable.
A4: SAMPLE
A5: Observations, weekly returns | B5: =COUNT([1]Data!D5:D303) -> 260
A7: RAW REGRESSION, EPR against OSEBX
A8: Raw equity beta | B8: =IFERROR(SLOPE('Price Data'!$D$6:$D265,'Price Data'!$E$6:$E$265),"") -> 0.47190074
A9: Alpha, per week | B9: =IFERROR(INTERCEPT('Price Data'!$D$6:$D$265,'Price Data'!$E$6:$E$265),"") -> 0.0019154378
A10: R squared | B10: =IFERROR(RSQ('Price Data'!$D$6:$D$265,'Price Data'!E$6:$E$265),"") -> 0.059676808
A11: Standard error of beta | B11: =IFERROR(STEYX('Price Data'!$D$6:$D$265,'Price Data'!$E$6:$E$265)/SQRT(DEVSQ('Price Data'!$E$6:$E$265)),"") -> 0.11662095
A12: t statistic | B12: =IFERROR(B8/B11,"") -> 4.046449
A13: 95 per cent lower bound | B13: =IFERROR(B8-1.96*B11,"") -> 0.24332367
A14: 95 per cent upper bound | B14: =IFERROR(B8+1.96*B11,"") -> 0.70047781
A16: ADJUSTED
A17: Blume adjusted beta | B17: =IFERROR(0.67*B8+0.33*1,"") -> 0.6461735

Sheet Assumptions
A1: Forecast assumptions and cost of capital
A2: This tab presents the main assumptions used to forecast Europris and calculate its cost of capital.
A4: Driver | C4: FY2026E | D4: FY2027E | E4: FY2028E | F4: FY2029E | G4: FY2030E | I4: Source and check
A6: REVENUE DRIVERS
A7: Norway sales growth | C7: 0.055 | D7: 0.045 | E7: 0.042 | F7: 0.04 | G7: 0.038 | I7: Europris Norway sales increased 7.2% in 2025 and 6.0% in H1 2026. Management targets above-market like-for-like growth and approximately five net new stores annually. Europris H1 2026
A8: Sweden sales growth | C8: 0.01 | D8: 0.1 | E8: 0.12 | F8: 0.04 | G8: 0.035 | I8: H1 2026 local-currency sales increased 0.7%, despite 24 temporary store closures. Management targets SEK 5 billion of sales by the end of 2028. Europris H1 2026
A10: MARGIN DRIVERS
A11: Gross margin | C11: 0.415 | D11: 0.417 | E11: 0.42 | F11: 0.421 | G11: 0.422 | I11: Group margin was 40.9% in 2025 and 41.0% in H1 2026. Sweden’s H1 margin improved to 33.1%, but remains below Norway’s margin. Europris Q2 2026
A12: Cash operating expenses including rent as share of income | C12: 0.323 | D12: 0.318 | E12: 0.311 | F12: 0.309 | G12: 0.308 | I12: Group opex was 24.9% of sales in 2025. Store closures and remodelling costs weigh on 2026, with improvement expected from 2027. Europris FY2025 results. Includes estimated store rent of 7.2% of income.
A13: Non-lease depreciation and amortisation as share of income | C13: 0.011 | D13: 0.011 | E13: 0.011 | F13: 0.011 | G13: 0.011 | I13: Historical calibration: 6.6%, 6.8%, 7.1%, 7.2% and 7.1%. Most depreciation relates to IFRS 16 right-of-use assets.Excludes IFRS 16 right-of-use depreciation because cash rent is included in operating expenses.
A15: CASH FLOW DRIVERS
A16: Capital expenditure as share of income | C16: 0.013 | D16: 0.012 | E16: 0.01 | F16: 0.01 | G16: 0.01 | I16: 2025 capex was approximately 0.9% of sales. Forecast is raised during the ÖoB remodelling period and then returns toward the historical level. Europris annual reports
A17: Change in working capital as share of change in income | C17: 0.12 | D17: 0.12 | E17: 0.11 | F17: 0.1 | G17: 0.1 | I17: Working capital absorbed approximately 18.6% of incremental income in 2025 and 6.4% in 2024. A low-to-mid-teens assumption reflects Europris’s inventory-heavy model.
A18: Effective tax rate | C18: 0.22 | D18: 0.22 | E18: 0.22 | F18: 0.22 | G18: 0.22 | I18: Norwegian ordinary company income is taxed at 22%. Norwegian Tax Administration
A20: COST OF CAPITAL
A21: Risk free rate | C21: 0.0439 | I21: Norwegian ten-year government bond yield was 4.392% on 28 August 2026. Norges Bank
A22: Equity risk premium | C22: 0.05 | I22: PwC’s 2025 Norwegian market-risk-premium survey reported a median of 5.0%. PwC Norway
A23: Equity beta | C23: =Beta!B17 -> 0.6461735 | I23: Market providers report lower historical betas of approximately 0.34–0.49. The base case normalises beta upward to 0.70 because Europris changed materially following full consolidation of ÖoB. Yahoo Finance beta
A24: Cost of equity | C24: =C21+C23*C22 -> 0.076208675 | I24: CAPM calculation using the risk-free rate, beta and equity risk premium.
A25: Pre tax cost of debt | C25: 0.055 | I25: Europris has a NOK 1.0bn term loan and NOK 2.2bn revolving facilities. Part of the term loan is interest-rate hedged. Europris capital management
A26: Marginal tax rate | C26: 0.22 | I26: Norwegian corporate tax rate. Norwegian Tax Administration
A27: After tax cost of debt | C27: =C25*(1-C26) -> 0.0429 | I27: Calculated from the pre-tax cost of debt and marginal tax rate.
A28: Target equity weight | C28: =(C34*Historicals!G30)/(C34*Historicals!G30+Historicals!G28) -> 0.94441119 | I28: Market-value capital structure using Europris market capitalisation and interest-bearing debt including IFRS 16 lease liabilities.
A29: Target debt weight | C29: =1-C28 -> 0.055588814 | I29: Calculated as the remainder of total capital.
A30: Standard CAPM WACC | C30: =C24*C28+C27*C29 -> 0.074357085 | I30: Calculated using market-value capital weights, CAPM cost of equity and after-tax cost of debt.
A32: TERMINAL VALUE AND MARKET DATA
A33: Terminal growth rate | C33: 0.025 | I33: Based on approximately 2% long-term inflation plus modest real growth. It is below expected long-run nominal economic growth.
A34: Current share price, NOK | C34: 89.1 | I34: Europris closing share price on 28 August 2026. Euronext
A35: Valuation date | C35: 46262 | I35: Last completed trading day used for the share price and government-bond yield.

Sheet Forecast
A1: Forecast income statement
A2: This tab forecasts Europris’s revenue, costs and operating profit based on the selected assumptions.
A4: Line item | C4: FY2026E | D4: FY2027E | E4: FY2028E | F4: FY2029E | G4: FY2030E
A6: Segment Norway sales | C6: =Historicals!$G$7*(1+Assumptions!C7) -> 11172.45 | D6: =C6*(1+Assumptions!D7) -> 11675.21 | E6: =D6*(1+Assumptions!E7) -> 12165.569 | F6: =E6*(1+Assumptions!F7) -> 12652.192 | G6: =F6*(1+Assumptions!G7) -> 13132.975
A7: Segment Sweden sales | C7: =Historicals!$G$8*(1+Assumptions!C8) -> 4331.89 | D7: =C7*(1+Assumptions!D8) -> 4765.079 | E7: =D7*(1+Assumptions!E8) -> 5336.8885 | F7: =E7*(1+Assumptions!F8) -> 5550.364 | G7: =F7*(1+Assumptions!G8) -> 5744.6268
A8: Total operating income | C8: =C6+C7 -> 15504.34 | D8: =D6+D7 -> 16440.289 | E8: =E6+E7 -> 17502.458 | F8: =F6+F7 -> 18202.556 | G8: =G6+G7 -> 18877.602
A9: Cost of goods sold | C9: =C8-C10 -> 9070.0389 | D9: =D8-D10 -> 9584.6886 | E9: =E8-E10 -> 10151.425 | F9: =F8-F10 -> 10539.28 | G9: =G8-G10 -> 10911.254
A10: Gross profit | C10: =C8*Assumptions!C11 -> 6434.3011 | D10: =D8*Assumptions!D11 -> 6855.6006 | E10: =E8*Assumptions!E11 -> 7351.0322 | F10: =F8*Assumptions!F11 -> 7663.276 | G10: =G8*Assumptions!G11 -> 7966.348
A11: Gross margin | C11: =IFERROR(C10/C8,"") -> 0.415 | D11: =IFERROR(D10/D8,"") -> 0.417 | E11: =IFERROR(E10/E8,"") -> 0.42 | F11: =IFERROR(F10/F8,"") -> 0.421 | G11: =IFERROR(G10/G8,"") -> 0.422
A12: Operating expenses | C12: =C8*Assumptions!C12 -> 5007.9018 | D12: =D8*Assumptions!D12 -> 5228.012 | E12: =E8*Assumptions!E12 -> 5443.2643 | F12: =F8*Assumptions!F12 -> 5624.5898 | G12: =G8*Assumptions!G12 -> 5814.3014
A13: EBITDA | C13: =C10-C12 -> 1426.3993 | D13: =D10-D12 -> 1627.5886 | E13: =E10-E12 -> 1907.7679 | F13: =F10-F12 -> 2038.6863 | G13: =G10-G12 -> 2152.0466
A14: EBITDA margin | C14: =IFERROR(C13/C8,"") -> 0.092 | D14: =IFERROR(D13/D8,"") -> 0.099 | E14: =IFERROR(E13/E8,"") -> 0.109 | F14: =IFERROR(F13/F8,"") -> 0.112 | G14: =IFERROR(G13/G8,"") -> 0.114
A15: Depreciation and amortisation | C15: =C8*Assumptions!C13 -> 170.54774 | D15: =D8*Assumptions!D13 -> 180.84318 | E15: =E8*Assumptions!E13 -> 192.52703 | F15: =F8*Assumptions!F13 -> 200.22811 | G15: =G8*Assumptions!G13 -> 207.65362
A16: EBIT | C16: =C13-C15 -> 1255.8515 | D16: =D13-D15 -> 1446.7455 | E16: =E13-E15 -> 1715.2408 | F16: =F13-F15 -> 1838.4581 | G16: =G13-G15 -> 1944.393
A17: EBIT margin | C17: =IFERROR(C16/C8,"") -> 0.081 | D17: =IFERROR(D16/D8,"") -> 0.088 | E17: =IFERROR(E16/E8,"") -> 0.098 | F17: =IFERROR(F16/F8,"") -> 0.101 | G17: =IFERROR(G16/G8,"") -> 0.103

Sheet DCF
A1: Unlevered free cash flow and valuation
A2: This tab calculates forecast free cash flow and estimates Europris’s enterprise and equity value.
A4: Line item | C4: FY2026E | D4: FY2027E | E4: FY2028E | F4: FY2029E | G4: FY2030E
A6: EBIT | C6: =Forecast!C16 -> 1255.8515 | D6: =Forecast!D16 -> 1446.7455 | E6: =Forecast!E16 -> 1715.2408 | F6: =Forecast!F16 -> 1838.4581 | G6: =Forecast!G16 -> 1944.393
A7: Effective tax rate | C7: =Assumptions!C18 -> 0.22 | D7: =Assumptions!D18 -> 0.22 | E7: =Assumptions!E18 -> 0.22 | F7: =Assumptions!F18 -> 0.22 | G7: =Assumptions!G18 -> 0.22
A8: Tax on EBIT | C8: =-C6*C7 -> -276.28734 | D8: =-D6*D7 -> -318.284 | E8: =-E6*E7 -> -377.35299 | F8: =-F6*F7 -> -404.46079 | G8: =-G6*G7 -> -427.76646
A9: NOPAT | C9: =C6+C8 -> 979.5642 | D9: =D6+D8 -> 1128.4615 | E9: =E6+E8 -> 1337.8879 | F9: =F6+F8 -> 1433.9974 | G9: =G6+G8 -> 1516.6265
A10: Add back non-lease depreciation and amortisation | C10: =Forecast!C15 -> 170.54774 | D10: =Forecast!D15 -> 180.84318 | E10: =Forecast!E15 -> 192.52703 | F10: =Forecast!F15 -> 200.22811 | G10: =Forecast!G15 -> 207.65362
A11: Less capital expenditure | C11: =-Forecast!C8*Assumptions!C16 -> -201.55642 | D11: =-Forecast!D8*Assumptions!D16 -> -197.28347 | E11: =-Forecast!E8*Assumptions!E16 -> -175.02458 | F11: =-Forecast!F8*Assumptions!F16 -> -182.02556 | G11: =-Forecast!G8*Assumptions!G16 -> -188.77602
A12: Less change in working capital | C12: =-(Forecast!C8-Historicals!$G$10)*Assumptions!C17 -> -75.1608 | D12: =-(Forecast!D8-Forecast!C8)*Assumptions!D17 -> -112.31391 | E12: =-(Forecast!E8-Forecast!D8)*Assumptions!E17 -> -116.83851 | F12: =-(Forecast!F8-Forecast!E8)*Assumptions!F17 -> -70.00983 | G12: =-(Forecast!G8-Forecast!F8)*Assumptions!G17 -> -67.504603
A13: Unlevered free cash flow | C13: =C9+C10+C11+C12 -> 873.39472 | D13: =D9+D10+D11+D12 -> 999.70725 | E13: =E9+E10+E11+E12 -> 1238.5518 | F13: =F9+F10+F11+F12 -> 1382.1901 | G13: =G9+G10+G11+G12 -> 1467.9995
A14: Discount period | C14: 1 | D14: 2 | E14: 3 | F14: 4 | G14: 5
A15: Discount factor | C15: =IFERROR(1/(1+Assumptions!$C$30)^C14,"") -> 0.93078923 | D15: =IFERROR(1/(1+Assumptions!$C$30)^D14,"") -> 0.86636858 | E15: =IFERROR(1/(1+Assumptions!$C$30)^E14,"") -> 0.80640654 | F15: =IFERROR(1/(1+Assumptions!$C$30)^F14,"") -> 0.75059452 | G15: =IFERROR(1/(1+Assumptions!$C$30)^G14,"") -> 0.6986453
A16: Present value of free cash flow | C16: =IFERROR(C13*C15,"") -> 812.9464 | D16: =IFERROR(D13*D15,"") -> 866.11496 | E16: =IFERROR(E13*E15,"") -> 998.77628 | F16: =IFERROR(F13*F15,"") -> 1037.4643 | G16: =IFERROR(G13*G15,"") -> 1025.611
A18: VALUATION BRIDGE
A19: Sum of present value of forecast cash flows | C19: =SUM($C$16:$G$16) -> 4740.9129
A20: Terminal value at end of forecast | C20: =G13*(1+Assumptions!C33)/(Assumptions!C30-Assumptions!C33) -> 30485.988
A21: Present value of terminal value | C21: =IFERROR(C20*$G$15,"") -> 21298.892
A22: Enterprise value | C22: =IFERROR(C19+C21,"") -> 26039.805
A23: Less net interest bearing debt | C23: =-Historicals!$G$28 -> -858
A24: Equity value | C24: =IFERROR(C22+C23,"") -> 25181.805
A25: Shares outstanding, million | C25: =Historicals!$G$30 -> 163.6
A26: Implied value per share, NOK | C26: =IFERROR(C24/C25,"") -> 153.92302
A27: Current share price, NOK | C27: =Assumptions!C34 -> 89.1
A28: Upside to current price | C28: =IFERROR(C26/C27-1,"") -> 0.72753103
A29: Terminal value as share of enterprise value | C29: =IFERROR(C21/C22,"") -> 0.81793593

Sheet Sensitivity
A1: Implied value per share, NOK
A2: This shows the estimated value of one Europris share based on the DCF valuation.
C4: Terminal growth rate
A5: WACC | C5: 0.01 | D5: 0.015 | E5: 0.02 | F5: 0.025 | G5: 0.03
B6: 0.07 | C6: =IFERROR((NPV($B6,DCF!$C$13:$G$13)+(DCF!$G$13*(1+C$5)/($B6-C$5))/(1+$B6)^5-Historicals!$G$28)/Historicals!$G$30,"n/a") -> 131.7997 | D6: =IFERROR((NPV($B6,DCF!$C$13:$G$13)+(DCF!$G$13*(1+D$5)/($B6-D$5))/(1+$B6)^5-Historicals!$G$28)/Historicals!$G$30,"n/a") -> 142.17172 | E6: =IFERROR((NPV($B6,DCF!$C$13:$G$13)+(DCF!$G$13*(1+E$5)/($B6-E$5))/(1+$B6)^5-Historicals!$G$28)/Historicals!$G$30,"n/a") -> 154.61815 | F6: =IFERROR((NPV($B6,DCF!$C$13:$G$13)+(DCF!$G$13*(1+F$5)/($B6-F$5))/(1+$B6)^5-Historicals!$G$28)/Historicals!$G$30,"n/a") -> 169.83045 | G6: =IFERROR((NPV($B6,DCF!$C$13:$G$13)+(DCF!$G$13*(1+G$5)/($B6-G$5))/(1+$B6)^5-Historicals!$G$28)/Historicals!$G$30,"n/a") -> 188.84583
B7: 0.08 | C7: =IFERROR((NPV($B7,DCF!$C$13:$G$13)+(DCF!$G$13*(1+C$5)/($B7-C$5))/(1+$B7)^5-Historicals!$G$28)/Historicals!$G$30,"n/a") -> 111.37874 | D7: =IFERROR((NPV($B7,DCF!$C$13:$G$13)+(DCF!$G$13*(1+D$5)/($B7-D$5))/(1+$B7)^5-Historicals!$G$28)/Historicals!$G$30,"n/a") -> 118.62654 | E7: =IFERROR((NPV($B7,DCF!$C$13:$G$13)+(DCF!$G$13*(1+E$5)/($B7-E$5))/(1+$B7)^5-Historicals!$G$28)/Historicals!$G$30,"n/a") -> 127.0823 | F7: =IFERROR((NPV($B7,DCF!$C$13:$G$13)+(DCF!$G$13*(1+F$5)/($B7-F$5))/(1+$B7)^5-Historicals!$G$28)/Historicals!$G$30,"n/a") -> 137.07548 | G7: =IFERROR((NPV($B7,DCF!$C$13:$G$13)+(DCF!$G$13*(1+G$5)/($B7-G$5))/(1+$B7)^5-Historicals!$G$28)/Historicals!$G$30,"n/a") -> 149.0673
B8: 0.09 | C8: =IFERROR((NPV($B8,DCF!$C$13:$G$13)+(DCF!$G$13*(1+C$5)/($B8-C$5))/(1+$B8)^5-Historicals!$G$28)/Historicals!$G$30,"n/a") -> 96.087281 | D8: =IFERROR((NPV($B8,DCF!$C$13:$G$13)+(DCF!$G$13*(1+D$5)/($B8-D$5))/(1+$B8)^5-Historicals!$G$28)/Historicals!$G$30,"n/a") -> 101.38459 | E8: =IFERROR((NPV($B8,DCF!$C$13:$G$13)+(DCF!$G$13*(1+E$5)/($B8-E$5))/(1+$B8)^5-Historicals!$G$28)/Historicals!$G$30,"n/a") -> 107.43866 | F8: =IFERROR((NPV($B8,DCF!$C$13:$G$13)+(DCF!$G$13*(1+F$5)/($B8-F$5))/(1+$B8)^5-Historicals!$G$28)/Historicals!$G$30,"n/a") -> 114.42412 | G8: =IFERROR((NPV($B8,DCF!$C$13:$G$13)+(DCF!$G$13*(1+G$5)/($B8-G$5))/(1+$B8)^5-Historicals!$G$28)/Historicals!$G$30,"n/a") -> 122.57383
B9: 0.1 | C9: =IFERROR((NPV($B9,DCF!$C$13:$G$13)+(DCF!$G$13*(1+C$5)/($B9-C$5))/(1+$B9)^5-Historicals!$G$28)/Historicals!$G$30,"n/a") -> 84.214554 | D9: =IFERROR((NPV($B9,DCF!$C$13:$G$13)+(DCF!$G$13*(1+D$5)/($B9-D$5))/(1+$B9)^5-Historicals!$G$28)/Historicals!$G$30,"n/a") -> 88.220273 | E9: =IFERROR((NPV($B9,DCF!$C$13:$G$13)+(DCF!$G$13*(1+E$5)/($B9-E$5))/(1+$B9)^5-Historicals!$G$28)/Historicals!$G$30,"n/a") -> 92.726707 | F9: =IFERROR((NPV($B9,DCF!$C$13:$G$13)+(DCF!$G$13*(1+F$5)/($B9-F$5))/(1+$B9)^5-Historicals!$G$28)/Historicals!$G$30,"n/a") -> 97.833998 | G9: =IFERROR((NPV($B9,DCF!$C$13:$G$13)+(DCF!$G$13*(1+G$5)/($B9-G$5))/(1+$B9)^5-Historicals!$G$28)/Historicals!$G$30,"n/a") -> 103.6709
B10: 0.11 | C10: =IFERROR((NPV($B10,DCF!$C$13:$G$13)+(DCF!$G$13*(1+C$5)/($B10-C$5))/(1+$B10)^5-Historicals!$G$28)/Historicals!$G$30,"n/a") -> 74.734134 | D10: =IFERROR((NPV($B10,DCF!$C$13:$G$13)+(DCF!$G$13*(1+D$5)/($B10-D$5))/(1+$B10)^5-Historicals!$G$28)/Historicals!$G$30,"n/a") -> 77.845114 | E10: =IFERROR((NPV($B10,DCF!$C$13:$G$13)+(DCF!$G$13*(1+E$5)/($B10-E$5))/(1+$B10)^5-Historicals!$G$28)/Historicals!$G$30,"n/a") -> 81.301757 | F10: =IFERROR((NPV($B10,DCF!$C$13:$G$13)+(DCF!$G$13*(1+F$5)/($B10-F$5))/(1+$B10)^5-Historicals!$G$28)/Historicals!$G$30,"n/a") -> 85.165064 | G10: =IFERROR((NPV($B10,DCF!$C$13:$G$13)+(DCF!$G$13*(1+G$5)/($B10-G$5))/(1+$B10)^5-Historicals!$G$28)/Historicals!$G$30,"n/a") -> 89.511285
